setup.py
gootool/__init__.py
gootool/drive.py
gootool/google_service.py
gootool/search.py
gootool/youtube.py
gootool.egg-info/PKG-INFO
gootool.egg-info/SOURCES.txt
gootool.egg-info/dependency_links.txt
gootool.egg-info/not-zip-safe
gootool.egg-info/top_level.txt