Metadata-Version: 1.0
Name: gootool
Version: 0.1.0
Summary: The Google Drive and Youtube tools with Google newest API.
Home-page: http://github.coom/leVirve/GooTool
Author: Salas leVirve
Author-email: gae.m.project@gmail.com
License: MIT
Platform: UNKNOWN
